Metadata-Version: 1.0
Name: JsonFlatten-xh
Version: 0.0.0
Summary: This is tool to flatten json data.
Home-page: https://github.com/Alfonsxh/JsonFlatten
Author: Alfons
Author-email: xiaohuihui100@gmail.com
License: UNKNOWN
Platform: UNKNOWN
